{
    "url":  "https://www.lemon8-app.com/@sistersguide/7506929744824009224?region=th",
    "downloadedAt":  "2026-07-10T14:54:00.820+08:00",
    "username":  "sistersguide",
    "author":  "Sistersguide",
    "images":  [
                   {
                       "url":  "https://p16-lemon8-sign-sg.tiktokcdn.com/tos-alisg-v-a3e477-sg/oYBDmxDtFABNW8bxAbAIJEg7V4cIQgAfAQfxeE~tplv-sdweummd6v-origin:QHNpc3RlcnNndWlkZQ==:1080:0.webp?lk3s=66c60501\u0026source=wap_large_logo_image\u0026x-expires=1786276800\u0026x-signature=ze%2Bubpvf1uCOoKoAT78ipgIeTqA%3D",
                       "width":  640,
                       "filename":  "01_640x640.webp",
                       "height":  640,
                       "index":  0
                   },
                   {
                       "url":  "https://p16-lemon8-sign-sg.tiktokcdn.com/tos-alisg-v-a3e477-sg/oUggWKubBIVc78xDEQfAemD4FNfAJExABQxbAx~tplv-sdweummd6v-origin:QHNpc3RlcnNndWlkZQ==:1080:0.webp?lk3s=66c60501\u0026source=wap_large_logo_image\u0026x-expires=1786276800\u0026x-signature=v8jqTMiSSqh5vMciuTiMSzYsLRE%3D",
                       "width":  640,
                       "filename":  "02_640x640.webp",
                       "height":  640,
                       "index":  1
                   },
                   {
                       "url":  "https://p16-lemon8-sign-sg.tiktokcdn.com/tos-alisg-v-a3e477-sg/oYfWefNgWEDFcrMIAQgA4AJ2BVmAYQjxD7bbEB~tplv-sdweummd6v-origin:QHNpc3RlcnNndWlkZQ==:1080:0.webp?lk3s=66c60501\u0026source=wap_large_logo_image\u0026x-expires=1786276800\u0026x-signature=GiTH3ZO%2FTUyXE79zkVYYNH7nYbw%3D",
                       "width":  640,
                       "filename":  "03_640x640.webp",
                       "height":  640,
                       "index":  2
                   },
                   {
                       "url":  "https://p16-lemon8-sign-sg.tiktokcdn.com/tos-alisg-v-a3e477-sg/oAemIgOVNDJx8xAsAfF4DbQAB7gABEGWQcfrbE~tplv-sdweummd6v-origin:QHNpc3RlcnNndWlkZQ==:1080:0.webp?lk3s=66c60501\u0026source=wap_large_logo_image\u0026x-expires=1786276800\u0026x-signature=A%2Ft5E7rY2%2FgcfH1Wxpvkev5sBwQ%3D",
                       "width":  640,
                       "filename":  "04_640x640.webp",
                       "height":  640,
                       "index":  3
                   },
                   {
                       "url":  "https://p16-lemon8-sign-sg.tiktokcdn.com/tos-alisg-v-a3e477-sg/oAmWDf4N7ELgQYeBVAQAFExbI6bfJAgQBD2Acb~tplv-sdweummd6v-origin:QHNpc3RlcnNndWlkZQ==:1080:0.webp?lk3s=66c60501\u0026source=wap_large_logo_image\u0026x-expires=1786276800\u0026x-signature=X6U0VdGMQ9e%2BfBjiLAfqbRAWsrQ%3D",
                       "width":  640,
                       "filename":  "05_640x640.webp",
                       "height":  640,
                       "index":  4
                   }
               ],
    "articleClass":  "Gallery",
    "imageCount":  5,
    "title":  "ไอเดียแมทเสื้อผ้าตามเจ้าหญิงดิสนีย์😍",
    "articleId":  "7506929744824009224",
    "proxy":  "http://127.0.0.1:10090"
}
